{
  "id": 1,
  "title": "project1",
  "created": "2024-06-27T17:29:07.510365+03:30",
  "board": 1,
  "pages": [
    {
      "id": 1,
      "title": "page1",
      "created": "2024-06-27T17:29:17.695067+03:30",
      "project": 1,
      "lists": [
        {
          "id": 1,
          "title": "list1",
          "created": "2024-06-27T17:41:42.103911+03:30",
          "page": 1,
          "tasks": [
            {
              "id": 1,
              "title": "task1",
              "created": "2024-06-27T17:42:54.475193+03:30",
              "list": 1,
              "state": "Todo"
            }
          ]
        }
      ]
    }
  ]
}
